bcd_to_excess3.v
module bcd_to_excess3( 
    input [3:0]a ,
    output [3:0]e 
);
assign e[3] = (a[3])|(a[2]&a[1])|(a[2]&a[0]) ;
assign e[2] = (~a[2]&a[1])|(~a[2]&a[0])|(a[2]&~a[1]&~a[0]);
assign e[1] = (a[1]&a[0])|(~a[1]&~a[0]);
assign e[0] = ~a[0] ;
endmodule

bcd_to_excess3_tb.v
`timescale 1ps/1ps
`include "bcd_to_excess3.v"

module bcd_to_excess3_tb ;
reg [3:0]a ;
wire [3:0]e ;

bcd_to_excess3 uut (
    .a(a),
    .e(e)
);

initial begin 
    $dumpfile("bcd_to_excess3.vcd");
    $dumpvars(0 , bcd_to_excess3_tb);

    $display("=======================================");
    $display("  BCD Input |  Excess-3 Output        ");
    $display ("======================================");
    $monitor ("  a = %b (%0d) | e = %b (%0d)", a, a, e, e);
    a = 4'b0000; #10;  // BCD 0 → Excess-3 = 0011 (3)
    a = 4'b0001; #10;  // BCD 1 → Excess-3 = 0100 (4)
    a = 4'b0010; #10;  // BCD 2 → Excess-3 = 0101 (5)
    a = 4'b0011; #10;  // BCD 3 → Excess-3 = 0110 (6)
    a = 4'b0100; #10;  // BCD 4 → Excess-3 = 0111 (7)
    a = 4'b0101; #10;  // BCD 5 → Excess-3 = 1000 (8)
    a = 4'b0110; #10;  // BCD 6 → Excess-3 = 1001 (9)
    a = 4'b0111; #10;  // BCD 7 → Excess-3 = 1010 (10)
    a = 4'b1000; #10;  // BCD 8 → Excess-3 = 1011 (11)
    a = 4'b1001; #10;  // BCD 9 → Excess-3 = 1100 (12)

        $display("=======================================");
        $display("        Simulation Complete!          ");
        $display("=======================================");
        $finish;
    end
endmodule

bcd_to_excess3.vcd
$date
	Wed Mar 18 00:20:17 2026
$end
$version
	Icarus Verilog
$end
$timescale
	1ps
$end
$scope module bcd_to_excess3_tb $end
$var wire 4 ! e [3:0] $end
$var reg 4 " a [3:0] $end
$scope module uut $end
$var wire 4 # a [3:0] $end
$var wire 4 $ e [3:0] $end
$upscope $end
$upscope $end
$enddefinitions $end
$comment Show the parameter values. $end
$dumpall
$end
#0
$dumpvars
b11 $
b0 #
b0 "
b11 !
$end
#10
b100 !
b100 $
b1 "
b1 #
#20
b101 !
b101 $
b10 "
b10 #
#30
b110 !
b110 $
b11 "
b11 #
#40
b111 !
b111 $
b100 "
b100 #
#50
b1000 !
b1000 $
b101 "
b101 #
#60
b1001 !
b1001 $
b110 "
b110 #
#70
b1010 !
b1010 $
b111 "
b111 #
#80
b1011 !
b1011 $
b1000 "
b1000 #
#90
b1100 !
b1100 $
b1001 "
b1001 #
