half_adder.v
module half_adder(a,b,carry , sum);
input a,b;
output sum , carry ;
assign sum = a^b ;
assign carry = a&b;
endmodule

full_adder.v
`include "half_adder.v"
module full_adder(a,b,Cin ,sum ,carry );

wire sum1 , carry1 , carry2 ;
input a,b,Cin ;
output sum , carry ;

half_adder ha1 (.a(a),.b(b), .sum(sum1) , .carry(carry1));
half_adder ha2 (.a(Cin) , .b(sum1), .sum(sum) , .carry(carry2));
assign carry = carry1 | carry2 ;
 

endmodule

full_adder_tb.v
`timescale 1ps/1ps
`include "full_adder.v"

module full_adder_tb ;
reg a , b , Cin ;
wire sum , carry ;

full_adder uut (.a(a), .b(b) ,.Cin(Cin) , .sum(sum) , .carry(carry));

initial begin 
    $dumpfile("full_adder.vcd");
    $dumpvars(0 , full_adder_tb);

    $display("a b Cin | sum carry ");
    $display("--------|----------");
    a=0; b=0; Cin=0; #10 $display("%b %b %b   | %b   %b", a, b, Cin, sum, carry );
    a=0; b=0; Cin=1; #10 $display("%b %b %b   | %b   %b", a, b, Cin, sum, carry );
    a=0; b=1; Cin=0; #10 $display("%b %b %b   | %b   %b", a, b, Cin, sum, carry );
    a=0; b=1; Cin=1; #10 $display("%b %b %b   | %b   %b", a, b, Cin, sum, carry );
    a=1; b=0; Cin=0; #10 $display("%b %b %b   | %b   %b", a, b, Cin, sum, carry );
    a=1; b=0; Cin=1; #10 $display("%b %b %b   | %b   %b", a, b, Cin, sum, carry );
    a=1; b=1; Cin=0; #10 $display("%b %b %b   | %b   %b", a, b, Cin, sum, carry );
    a=1; b=1; Cin=1; #10 $display("%b %b %b   | %b   %b", a, b, Cin, sum, carry );

    $display ("yo damn nigga ");
    $finish;
end
endmodule

full_adder.vcd
$date
	Wed Feb 11 20:37:21 2026
$end
$version
	Icarus Verilog
$end
$timescale
	1ps
$end
$scope module full_adder_tb $end
$var wire 1 ! sum $end
$var wire 1 " carry $end
$var reg 1 # Cin $end
$var reg 1 $ a $end
$var reg 1 % b $end
$scope module uut $end
$var wire 1 # Cin $end
$var wire 1 $ a $end
$var wire 1 % b $end
$var wire 1 " carry $end
$var wire 1 & sum1 $end
$var wire 1 ! sum $end
$var wire 1 ' carry2 $end
$var wire 1 ( carry1 $end
$scope module ha1 $end
$var wire 1 $ a $end
$var wire 1 % b $end
$var wire 1 ( carry $end
$var wire 1 & sum $end
$upscope $end
$scope module ha2 $end
$var wire 1 # a $end
$var wire 1 & b $end
$var wire 1 ' carry $end
$var wire 1 ! sum $end
$upscope $end
$upscope $end
$upscope $end
$enddefinitions $end
$comment Show the parameter values. $end
$dumpall
$end
#0
$dumpvars
0(
0'
0&
0%
0$
0#
0"
0!
$end
#10
1!
1#
#20
1&
0#
1%
#30
1"
0!
1'
1#
#40
0"
1!
0'
0#
0%
1$
#50
1"
0!
1'
1#
#60
0'
0&
1(
0#
1%
#70
1!
1#
