mux_2_1.v
module mux_2_1(sel ,a,b, y);
input a,b,sel ;
output y ;
assign y = (~sel&a)|(sel&b);
//here we took a as low and b as high .
endmodule

mux_2_1_tb.v
`timescale 1ps/1ps
`include "mux_2_1.v"

module mux_2_1_tb ;

reg a,b ,sel ;
wire y ;

mux_2_1 uut (
    .a(a), 
    .b(b),
    .sel(sel),
    .y(y)
);

initial begin 
    $dumpfile("mux_2_1.vcd");
    $dumpvars(0,mux_2_1_tb);


    $display("Time\t a\t b\t sel\t y");
    $display("--------------------------------");
     a = 0; b = 0; sel = 0; #10;
     a = 0; b = 0; sel = 1; #10;
     a = 0; b = 1; sel = 0; #10;
     a = 0; b = 1; sel = 1; #10;
     a = 1; b = 0; sel = 0; #10;
     a = 1; b = 0; sel = 1; #10;
     a = 1; b = 1; sel = 0; #10;
     a = 1; b = 1; sel = 1; #10;

     $display("damn bro u did it again");
     $finish;
end
endmodule

mux_2_1.vcd
$date
	Wed Feb 11 01:19:43 2026
$end
$version
	Icarus Verilog
$end
$timescale
	1ps
$end
$scope module mux_2_1_tb $end
$var wire 1 ! y $end
$var reg 1 " a $end
$var reg 1 # b $end
$var reg 1 $ sel $end
$scope module uut $end
$var wire 1 " a $end
$var wire 1 # b $end
$var wire 1 $ sel $end
$var wire 1 ! y $end
$upscope $end
$upscope $end
$enddefinitions $end
$comment Show the parameter values. $end
$dumpall
$end
#0
$dumpvars
0$
0#
0"
0!
$end
#10
1$
#20
0$
1#
#30
1!
1$
#40
1!
0$
0#
1"
#50
0!
1$
#60
1!
0$
1#
#70
1$
